thinknet_observer/__init__.py
thinknet_observer/calulator.py
thinknet_observer/loggers/__init__.py
thinknet_observer/loggers/accesslog.py
thinknet_observer/loggers/logger.py
thinknet_observer/metrics/__init__.py
thinknet_observer/metrics/collector.py
thinknet_observer/metrics/config.py
thinknet_observer/metrics/custom_metrics_wrapper.py
thinknet_observer/metrics/fastapi_metrics_redirect.py
thinknet_observer/metrics/metrics.py
thinknet_observer/utils/__init__.py
thinknet_observer/utils/bcolor.py
thinknet_observer/utils/gunicorn_multiprocess.py
thinknet_observer/utils/singleton.py
thinknet_observer-0.4.21.dist-info/METADATA
thinknet_observer-0.4.21.dist-info/WHEEL
thinknet_observer-0.4.21.dist-info/top_level.txt
thinknet_observer-0.4.21.dist-info/RECORD
