Metadata-Version: 2.1
Name: thinknet-observer
Version: 0.4.21
Summary: lib in development
Home-page: https://gitlab.thinknet.co.th/big-data/thinknet-observer-python
Author: TN - DS Team
Author-email: nattawutd@thinknet.co.th
License: MIT
Platform: UNKNOWN
Classifier: Intended Audience :: Developers
Classifier: License :: OSI Approved :: MIT License
Classifier: Programming Language :: Python
Classifier: Programming Language :: Python :: 3
Classifier: Programming Language :: Python :: 3.7
Classifier: Programming Language :: Python :: 3.8
Classifier: Programming Language :: Python :: 3.9
Classifier: Operating System :: OS Independent
Requires-Dist: numpy
Requires-Dist: prometheus-client (==0.11.0)
Requires-Dist: Flask
Requires-Dist: fastapi
